cdhelm/__init__.py
cdhelm/cdhelm.py
cdhelm/helm.py
cdhelm-0.1.4.dist-info/LICENSE
cdhelm-0.1.4.dist-info/METADATA
cdhelm-0.1.4.dist-info/WHEEL
cdhelm-0.1.4.dist-info/top_level.txt
cdhelm-0.1.4.dist-info/RECORD
