Metadata-Version: 2.1
Name: cdhelm
Version: 0.1.4
Summary: Helm interface in cdk8s
Home-page: https://github.com/fulso-me/cdhelm
Author: Brian Robertson
Author-email: brian@fulso.me
License: UNKNOWN
Keywords: cdk8s helm kubernetes k8s
Platform: UNKNOWN
Classifier: Programming Language :: Python :: 3
Classifier: License :: OSI Approved :: MIT License
Classifier: Operating System :: OS Independent
Requires-Python: >=3.6
Requires-Dist: cdk8s
Requires-Dist: pyyaml
